LICENSE
MANIFEST.in
README.md
scrapy.cfg
setup.cfg
setup.py
os_scrapy_spage/__init__.py
os_scrapy_spage/items.py
os_scrapy_spage/middlewares.py
os_scrapy_spage/pipelines.py
os_scrapy_spage/settings.py
os_scrapy_spage/utils.py
os_scrapy_spage.egg-info/PKG-INFO
os_scrapy_spage.egg-info/SOURCES.txt
os_scrapy_spage.egg-info/dependency_links.txt
os_scrapy_spage.egg-info/not-zip-safe
os_scrapy_spage.egg-info/requires.txt
os_scrapy_spage.egg-info/top_level.txt
os_scrapy_spage/spiders/__init__.py
requirements/requirements-lint.txt
requirements/requirements-test.txt
requirements/requirements.txt
tests/__init__.py
tests/test_scrapy_check.py